avnet.py
avnet-0.1.0.dist-info/METADATA
avnet-0.1.0.dist-info/WHEEL
avnet-0.1.0.dist-info/top_level.txt
avnet-0.1.0.dist-info/RECORD
