Metadata-Version: 2.4
Name: avnet
Version: 0.1.0
Summary: Developer Toolbelt
Requires-Python: >=3.14
